setup.py
recast_database.egg-info/PKG-INFO
recast_database.egg-info/SOURCES.txt
recast_database.egg-info/dependency_links.txt
recast_database.egg-info/requires.txt
recast_database.egg-info/top_level.txt
recastdb/__init__.py
recastdb/database.py
recastdb/models.py
tests/__init__.py