Metadata-Version: 1.0
Name: recast-database
Version: 0.1.0
Summary: database code for RECAST
Home-page: UNKNOWN
Author: Lukas Heinrich
Author-email: UNKNOWN
License: UNKNOWN
Platform: UNKNOWN
